bikerider/__init__.py
bikerider/main.py
bikerider-0.1.dist-info/METADATA
bikerider-0.1.dist-info/WHEEL
bikerider-0.1.dist-info/top_level.txt
bikerider-0.1.dist-info/RECORD
