Metadata-Version: 2.4
Name: bikerider
Version: 0.1
Summary: A simple Python helper package
Author: Abhi_456
Author-email: sattaruvenkataabhilash@gmail.com
Classifier: Programming Language :: Python :: 3
Classifier: License :: OSI Approved :: MIT License
Classifier: Operating System :: OS Independent
Requires-Python: >=3.6
Requires-Dist: pandas
Dynamic: author
Dynamic: author-email
Dynamic: classifier
Dynamic: description-content-type
Dynamic: requires-dist
Dynamic: requires-python
Dynamic: summary
